memas_sdk/__init__.py
memas_sdk/api_client.py
memas_sdk/configuration.py
memas_sdk/exceptions.py
memas_sdk/rest.py
memas_sdk/schemas.py
memas_sdk/apis/__init__.py
memas_sdk/apis/path_to_api.py
memas_sdk/apis/tag_to_api.py
memas_sdk/apis/paths/__init__.py
memas_sdk/apis/paths/cp_create_corpus.py
memas_sdk/apis/paths/cp_create_user.py
memas_sdk/apis/tags/__init__.py
memas_sdk/apis/tags/cp_api.py
memas_sdk/model/__init__.py
memas_sdk/model/corpus_pathname.py
memas_sdk/model/corpus_type.py
memas_sdk/model/namespace_pathname.py
memas_sdk/models/__init__.py
memas_sdk/paths/__init__.py
memas_sdk/paths/cp_create_corpus/__init__.py
memas_sdk/paths/cp_create_corpus/post.py
memas_sdk/paths/cp_create_user/__init__.py
memas_sdk/paths/cp_create_user/post.py
memas_sdk-0.1.1.dist-info/LICENSE
memas_sdk-0.1.1.dist-info/METADATA
memas_sdk-0.1.1.dist-info/WHEEL
memas_sdk-0.1.1.dist-info/top_level.txt
memas_sdk-0.1.1.dist-info/RECORD
